eigenrules/__init__.py
eigenrules/anomaly.py
eigenrules/exceptions.py
eigenrules/schemas.py
eigenrules/segmentation.py
eigenrules-0.1.13.dist-info/LICENSE
eigenrules-0.1.13.dist-info/METADATA
eigenrules-0.1.13.dist-info/WHEEL
eigenrules-0.1.13.dist-info/RECORD
